omni_bot_sdk/__init__.py
omni_bot_sdk/bot.py
omni_bot_sdk/models.py
omni_bot_sdk/clients/dify_client.py
omni_bot_sdk/clients/minio_client.py
omni_bot_sdk/clients/mqtt_client.py
omni_bot_sdk/common/__init__.py
omni_bot_sdk/common/config.py
omni_bot_sdk/common/exceptions.py
omni_bot_sdk/common/queues.py
omni_bot_sdk/mcp/__init__.py
omni_bot_sdk/mcp/app.py
omni_bot_sdk/mcp/dispatchers.py
omni_bot_sdk/mcp/protocols.py
omni_bot_sdk/plugins/__init__.py
omni_bot_sdk/plugins/interface.py
omni_bot_sdk/plugins/plugin_manager.py
omni_bot_sdk/plugins/core/__init__.py
omni_bot_sdk/plugins/core/block_empty_room_plugin.py
omni_bot_sdk/plugins/core/image_aes_plugin.py
omni_bot_sdk/plugins/core/plugin_interface.py
omni_bot_sdk/plugins/core/self_msg_plugin.py
omni_bot_sdk/rpa/__init__.py
omni_bot_sdk/rpa/controller.py
omni_bot_sdk/rpa/image_processor.py
omni_bot_sdk/rpa/input_handler.py
omni_bot_sdk/rpa/message_sender.py
omni_bot_sdk/rpa/ocr_processor.py
omni_bot_sdk/rpa/ui_helper.py
omni_bot_sdk/rpa/window_manager.py
omni_bot_sdk/rpa/action_handlers/__init__.py
omni_bot_sdk/rpa/action_handlers/announcement_handler.py
omni_bot_sdk/rpa/action_handlers/base_handler.py
omni_bot_sdk/rpa/action_handlers/download_file_handler.py
omni_bot_sdk/rpa/action_handlers/download_image_handler.py
omni_bot_sdk/rpa/action_handlers/download_video_handler.py
omni_bot_sdk/rpa/action_handlers/forward_message_handler.py
omni_bot_sdk/rpa/action_handlers/leave_room_handler.py
omni_bot_sdk/rpa/action_handlers/pat_handler.py
omni_bot_sdk/rpa/action_handlers/remove_room_member_handler.py
omni_bot_sdk/rpa/action_handlers/rename_name_in_room_handler.py
omni_bot_sdk/rpa/action_handlers/rename_room_name_handler.py
omni_bot_sdk/rpa/action_handlers/rename_room_remark_handler.py
omni_bot_sdk/rpa/action_handlers/send_file_handler.py
omni_bot_sdk/rpa/action_handlers/send_image_handler.py
omni_bot_sdk/rpa/action_handlers/send_text_message_handler.py
omni_bot_sdk/rpa/action_handlers/switch_conversation_handler.py
omni_bot_sdk-2.0.0.dist-info/licenses/LICENSE
omni_bot_sdk-2.0.0.dist-info/METADATA
omni_bot_sdk-2.0.0.dist-info/WHEEL
omni_bot_sdk-2.0.0.dist-info/entry_points.txt
omni_bot_sdk-2.0.0.dist-info/top_level.txt
omni_bot_sdk-2.0.0.dist-info/RECORD
