Metadata-Version: 2.4
Name: omni-bot-sdk
Version: 2.0.0
Summary: Core SDK for building Omni-channel RPA bots.
Author-email: huchundong <gycm520@gmail.com>
License-Expression: GPL-3.0-or-later
Project-URL: Homepage, https://github.com/weixin-omni/omni-bot-sdk-oss
Project-URL: Issues, https://github.com/weixin-omni/omni-bot-sdk-oss/issues
Classifier: Programming Language :: Python :: 3.12
Classifier: Operating System :: Microsoft :: Windows
Requires-Python: >=3.12
License-File: LICENSE
Requires-Dist: pyautogui==0.9.54
Requires-Dist: sqlcipher3-wheels==0.5.4.post0
Requires-Dist: ultralytics==8.3.161
Requires-Dist: fastmcp==2.10.1
Requires-Dist: paho-mqtt==2.1.0
Requires-Dist: protobuf==6.31.1
Requires-Dist: aiohttp==3.12.13
Requires-Dist: aiofiles==24.1.0
Requires-Dist: cryptography==45.0.5
Requires-Dist: lxml==6.0.0
Requires-Dist: minio==7.2.15
Requires-Dist: mss==10.0.0
Requires-Dist: fuzzywuzzy==0.18.0
Requires-Dist: xmltodict==0.14.2
Requires-Dist: yara-python==4.5.4
Requires-Dist: zstandard==0.23.0
Requires-Dist: pymem==1.14.0
Requires-Dist: pywin32==310
Requires-Dist: rapidocr==3.2.0
Requires-Dist: python-Levenshtein==0.27.1
Requires-Dist: watchfiles==1.1.0
Requires-Dist: onnxruntime==1.22.0
Requires-Dist: ruamel.yaml==0.18.14
Requires-Dist: pydantic==2.11.7
Requires-Dist: py-machineid==0.8.0
Requires-Dist: pyjwt==2.10.1
Requires-Dist: openai==1.93.0
Requires-Dist: boto3==1.39.3
Dynamic: license-file
